xdxf2html.cpython-314-darwin.so
xdxf2html-0.2.0.dist-info/RECORD
xdxf2html-0.2.0.dist-info/WHEEL
xdxf2html-0.2.0.dist-info/top_level.txt
xdxf2html-0.2.0.dist-info/METADATA
xdxf2html-0.2.0.dist-info/licenses/LICENSE.txt
