Metadata-Version: 2.4
Name: xdxf2html
Version: 0.2.0
Summary: XDXF to HTML conversion
Author-email: Yi Xing <blandilyte@gmail.com>
Project-URL: Homepage, https://github.com/Crissium/python-xdxf2html
Classifier: Programming Language :: C++
Classifier: License :: OSI Approved :: GNU General Public License v3 (GPLv3)
Classifier: Operating System :: OS Independent
Requires-Python: >=3.0
License-File: LICENSE.txt
Dynamic: license-file
